{
	"items":[
		{
			"type":"111",
			"url":"111",
			"login":"111",
			"password":"111",
			"description":" "
		}, {
			"type":"222",
			"url":"222",
			"login":"222",
			"password":"222",
			"description":" "
		}, {
			"type":"555",
			"url":"555",
			"login":"555",
			"password":"555",
			"description":" "
		}, {
			"type":"666",
			"url":"666",
			"login":"666",
			"password":"666",
			"description":" "
		}, {
			"type":"TYPE",
			"url":"url url url url url url url url url url url url url url",
			"login":"login login login login login login login login login",
			"password":"password password password password password password",
			"description":"description description description description"
		}
	]
}
